pypans/__init__.py
pypans/__main__.py
pypans/file.py
pypans/project.py
pypans/template/.flake8
pypans/template/.gitignore
pypans/template/.pydocstyle
pypans/template/.pylintrc
pypans/template/.pypirc
pypans/template/.travis.yml
pypans/template/AUTHORS.md
pypans/template/CHANGELOG.md
pypans/template/LICENSE.md
pypans/template/MANIFEST.in
pypans/template/Procfile
pypans/template/README.md
pypans/template/_config.yml
pypans/template/analyse-source-code.sh
pypans/template/icon.png
pypans/template/mypy.ini
pypans/template/pyproject.toml
pypans/template/pytest.ini
pypans/template/requirements-dev.txt
pypans/template/requirements.txt
pypans/template/runtime.txt
pypans/template/setup.py
pypans-0.0.15.dist-info/AUTHORS.md
pypans-0.0.15.dist-info/LICENSE.md
pypans-0.0.15.dist-info/METADATA
pypans-0.0.15.dist-info/WHEEL
pypans-0.0.15.dist-info/entry_points.txt
pypans-0.0.15.dist-info/top_level.txt
pypans-0.0.15.dist-info/RECORD
